{
	"configurations" : 
	[
		{
			"directories" : 
			[
				{
					"build" : ".",
					"hasInstallRule" : true,
					"jsonFile" : "directory-.-7ad7c0fb005c4c24ae10.json",
					"minimumCMakeVersion" : 
					{
						"string" : "3.12"
					},
					"projectIndex" : 0,
					"source" : ".",
					"targetIndexes" : 
					[
						0,
						1
					]
				}
			],
			"name" : "",
			"projects" : 
			[
				{
					"directoryIndexes" : 
					[
						0
					],
					"name" : "app_server",
					"targetIndexes" : 
					[
						0,
						1
					]
				}
			],
			"targets" : 
			[
				{
					"directoryIndex" : 0,
					"id" : "app_server_uninstall::@6890427a1f51a3e7e1df",
					"jsonFile" : "target-app_server_uninstall-91207e2f2e8e76016ffb.json",
					"name" : "app_server_uninstall",
					"projectIndex" : 0
				},
				{
					"directoryIndex" : 0,
					"id" : "uninstall::@6890427a1f51a3e7e1df",
					"jsonFile" : "target-uninstall-f2ac895255d9b38a3005.json",
					"name" : "uninstall",
					"projectIndex" : 0
				}
			]
		}
	],
	"kind" : "codemodel",
	"paths" : 
	{
		"build" : "/home/vedant/OdriveCANControl/build/app_server",
		"source" : "/home/vedant/OdriveCANControl/src/app_server"
	},
	"version" : 
	{
		"major" : 2,
		"minor" : 3
	}
}
